py_vcon_server/__init__.py
py_vcon_server/__main__.py
py_vcon_server/admin_api.py
py_vcon_server/job_worker_pool.py
py_vcon_server/logging_utils.py
py_vcon_server/pipeline.py
py_vcon_server/restful_api.py
py_vcon_server/settings.py
py_vcon_server/vcon_api.py
py_vcon_server/db/__init__.py
py_vcon_server/db/redis_registration.py
py_vcon_server/db/redis/__init__.py
py_vcon_server/db/redis/redis_mgr.py
py_vcon_server/pipeline_editor/__init__.py
py_vcon_server/pipeline_editor/index.css
py_vcon_server/pipeline_editor/index.html
py_vcon_server/pipeline_editor/index.js
py_vcon_server/processor/__init__.py
py_vcon_server/processor/create_amended.py
py_vcon_server/processor/decrypt.py
py_vcon_server/processor/deepgram.py
py_vcon_server/processor/encrypt.py
py_vcon_server/processor/jq.py
py_vcon_server/processor/openai.py
py_vcon_server/processor/queue_job.py
py_vcon_server/processor/send_email.py
py_vcon_server/processor/set_parameters.py
py_vcon_server/processor/sign.py
py_vcon_server/processor/text_pii_redactor.py
py_vcon_server/processor/verify.py
py_vcon_server/processor/whisper_base.py
py_vcon_server/processor/builtin/create_amended.py
py_vcon_server/processor/builtin/decrypt.py
py_vcon_server/processor/builtin/deepgram.py
py_vcon_server/processor/builtin/encrypt.py
py_vcon_server/processor/builtin/jq.py
py_vcon_server/processor/builtin/openai.py
py_vcon_server/processor/builtin/queue_job.py
py_vcon_server/processor/builtin/send_email.py
py_vcon_server/processor/builtin/set_parameters.py
py_vcon_server/processor/builtin/sign.py
py_vcon_server/processor/builtin/text_pii_redactor.py
py_vcon_server/processor/builtin/verify.py
py_vcon_server/processor/builtin/whisper.py
py_vcon_server/processor_addons/__init__.py
py_vcon_server/queue/__init__.py
py_vcon_server/states/__init__.py
py_vcon_server-0.5.0.data/data/py_vcon_server/pip_server_requirements.txt
py_vcon_server-0.5.0.data/data/py_vcon_server/pipeline_editor/index.css
py_vcon_server-0.5.0.dist-info/METADATA
py_vcon_server-0.5.0.dist-info/WHEEL
py_vcon_server-0.5.0.dist-info/top_level.txt
py_vcon_server-0.5.0.dist-info/RECORD
