Metadata-Version: 2.1
Name: py-vcon-server
Version: 0.5.0
Summary: server for vCon conversational data container manipulation package
Home-page: http://github.com/py-vcon/py-vcon/py_vcon_server
Author: Dan Petrie
Author-email: dan.vcon@sipez.com
License: MIT
Requires-Python: >=3.8
Requires-Dist: python-vcon
Requires-Dist: aiosmtplib
Requires-Dist: fastapi[all]
Requires-Dist: fastapi-utils
Requires-Dist: nest-asyncio
Requires-Dist: packaging
Requires-Dist: pkgutil-resolve-name
Requires-Dist: psutil
Requires-Dist: pydantic
Requires-Dist: pyjq
Requires-Dist: python-vcon >=0.6.0
Requires-Dist: redis
Requires-Dist: setuptools
Requires-Dist: smtpdfix
Requires-Dist: uvicorn
